gravhopper/__init__.py
gravhopper/_jbgrav.cpython-310-x86_64-linux-gnu.so
gravhopper/gravhopper.py
gravhopper/jbgrav.py
gravhopper/unitconverter.py
gravhopper-1.2.0.dist-info/METADATA
gravhopper-1.2.0.dist-info/WHEEL
gravhopper-1.2.0.dist-info/top_level.txt
gravhopper-1.2.0.dist-info/RECORD
gravhopper-1.2.0.dist-info/licenses/LICENSE
