Metadata-Version: 2.4
Name: gravhopper
Version: 1.2.0
Summary: Simple N-body code for Python
Home-page: https://github.com/jbailinua/gravhopper
Author: Jeremy Bailin
Author-email: jbailin@ua.edu
License: BSD
Classifier: Programming Language :: Python :: 3
Classifier: License :: OSI Approved :: BSD License
Requires-Python: >=3.7
License-File: LICENSE
Requires-Dist: numpy>=1.21
Requires-Dist: scipy>=1.10
Requires-Dist: matplotlib>=2.2
Requires-Dist: astropy>=4.0
Dynamic: author
Dynamic: author-email
Dynamic: classifier
Dynamic: description
Dynamic: description-content-type
Dynamic: home-page
Dynamic: license
Dynamic: license-file
Dynamic: requires-dist
Dynamic: requires-python
Dynamic: summary
